[
  {
    "name": "Chronic Hypertension",
    "uuid": "1f4227dc-a51f-4237-9217-37d4cea92efd",
    "dataType": "N/A"
  },
  {
    "name": "Chronic Hypertension with Superimposed Pre-Eclampsia",
    "uuid": "5c9992a0-56cd-4ce3-91df-631357649628",
    "dataType": "N/A"
  },
  {
    "name": "Pregnancy Induced Hypertension",
    "uuid": "35557870-2678-4578-9215-ae078dce194c",
    "dataType": "N/A"
  },
  {
    "name": "Mild Pre-Eclampsia",
    "uuid": "0eb43d96-dfff-4e45-91e8-1a273b419763",
    "dataType": "N/A"
  },
  {
    "name": "Severe Pre-Eclampsia",
    "uuid": "e6b24a5c-00f2-46c7-aa67-5b460df5cc81",
    "dataType": "N/A"
  },
  {
    "name": "Severe Anemia",
    "uuid": "1aff631c-e487-4202-a862-122b45168ac6",
    "dataType": "N/A"
  },
  {
    "name": "Moderate Anemia",
    "uuid": "c67d2c3a-c1c8-4cb7-b76e-b77e02541577",
    "dataType": "N/A"
  }
]